cpselect2/__init__.py
cpselect2/cpselect.py
cpselect2/help.html
cpselect2/img/backforwardbutton.png
cpselect2/img/cpselect32.ico
cpselect2/img/homebutton.png
cpselect2/img/navbuttons.PNG
cpselect2/img/panzoombutton.png
cpselect2/img/zoomboxbutton.png
cpselect2/test/__init__.py
cpselect2-1.0.6.dist-info/LICENSE
cpselect2-1.0.6.dist-info/METADATA
cpselect2-1.0.6.dist-info/WHEEL
cpselect2-1.0.6.dist-info/RECORD
