Metadata-Version: 2.1
Name: cpselect2
Version: 1.0.6
Summary: Matlab's cpselect alternative for Python
License: MIT
Author: arunoruto
Requires-Python: >=3.10,<4.0
Classifier: License :: OSI Approved :: MIT License
Classifier: Programming Language :: Python :: 3
Classifier: Programming Language :: Python :: 3.10
Classifier: Programming Language :: Python :: 3.11
Classifier: Programming Language :: Python :: 3.12
Requires-Dist: matplotlib (>=3.8.4,<4.0.0)
Requires-Dist: numpy (>=1.26.4,<2.0.0)
Requires-Dist: pillow (>=10.3.0,<11.0.0)
Requires-Dist: pyqt5 (==5.15.10)
Requires-Dist: pyqt5-qt5 (==5.15.2)
